ramos/__init__.py
ramos/compat.py
ramos/exceptions.py
ramos/mixins.py
ramos/pool.py
ramos-1.4.0.dist-info/LICENSE
ramos-1.4.0.dist-info/METADATA
ramos-1.4.0.dist-info/WHEEL
ramos-1.4.0.dist-info/top_level.txt
ramos-1.4.0.dist-info/RECORD
