Metadata-Version: 2.1
Name: ramos
Version: 1.4.0
Summary: Generic backend pool 
Home-page: https://github.com/luizalabs/ramos
Author: LuizaLabs
Author-email: pypi@luizalabs.com
License: UNKNOWN
Keywords: django backends pool
Platform: UNKNOWN
Classifier: Intended Audience :: Developers
Classifier: License :: OSI Approved :: MIT License
Classifier: Operating System :: OS Independent
Classifier: Programming Language :: Python :: 2
Classifier: Programming Language :: Python :: 3
Provides-Extra: django
Requires-Dist: Django (>=1.8) ; extra == 'django'
Provides-Extra: simple_settings
Requires-Dist: simple-settings ; extra == 'simple_settings'
